{"id":"IDFM:TN:SNCF:e451d166-81fd-414f-9eda-3f37a30d9e60","headsign":"Aulnay-sous-Bois","direction":"0","monday":0,"tuesday":0,"wednesday":0,"thursday":0,"friday":0,"saturday":1,"sunday":1,"start_date":20220402,"end_date":20220430,"dates":null,"exceptions":null,"stops":[{"id":"IDFM:72037","arrival":"16:26:15","departure":"16:26:15","sequence":0},{"id":"IDFM:72033","arrival":"16:27:15","departure":"16:27:45","sequence":1},{"id":"IDFM:72028","arrival":"16:29:25","departure":"16:29:55","sequence":2},{"id":"IDFM:73312","arrival":"16:31:35","departure":"16:32:05","sequence":3},{"id":"IDFM:73334","arrival":"16:33:45","departure":"16:34:15","sequence":4},{"id":"IDFM:73360","arrival":"16:35:45","departure":"16:36:45","sequence":5},{"id":"IDFM:411281","arrival":"16:38:55","departure":"16:39:25","sequence":6},{"id":"IDFM:73709","arrival":"16:41:00","departure":"16:41:30","sequence":7},{"id":"IDFM:73411","arrival":"16:42:40","departure":"16:43:10","sequence":8},{"id":"IDFM:411284","arrival":"16:44:30","departure":"16:45:00","sequence":9},{"id":"IDFM:72646","arrival":"16:46:45","departure":"16:46:45","sequence":10}]}