{"id":"IDFM:TN:SNCF:14104195-8b57-48f5-974c-afb578bb4e61","headsign":"Gare d'Epinay Villetaneuse","direction":"0","monday":0,"tuesday":0,"wednesday":0,"thursday":0,"friday":0,"saturday":1,"sunday":0,"start_date":20220430,"end_date":20220430,"dates":null,"exceptions":null,"stops":[{"id":"IDFM:66079","arrival":"12:25:00","departure":"12:25:00","sequence":0},{"id":"IDFM:65749","arrival":"12:34:00","departure":"12:34:00","sequence":1},{"id":"IDFM:65562","arrival":"12:46:00","departure":"12:46:00","sequence":2},{"id":"IDFM:65227","arrival":"13:01:00","departure":"13:01:00","sequence":3}]}