{"id":"IDFM:TN:SNCF:e87d0c9c-800b-4a3d-a908-3ec7c6db97d2","headsign":"Gare d'Ermont-Eaubonne","direction":"0","monday":0,"tuesday":0,"wednesday":0,"thursday":0,"friday":0,"saturday":1,"sunday":1,"start_date":20220402,"end_date":20220403,"dates":null,"exceptions":null,"stops":[{"id":"IDFM:72206","arrival":"22:10:00","departure":"22:10:00","sequence":0},{"id":"IDFM:65227","arrival":"22:33:00","departure":"22:33:00","sequence":1},{"id":"IDFM:65669","arrival":"22:50:00","departure":"22:50:00","sequence":2}]}