{"id":"IDFM:TN:SNCF:d4213082-f6e4-49ae-8dc8-1dc920c05d3e","headsign":"Aulnay-sous-Bois","direction":"0","monday":0,"tuesday":0,"wednesday":0,"thursday":0,"friday":0,"saturday":1,"sunday":1,"start_date":20220402,"end_date":20220430,"dates":null,"exceptions":null,"stops":[{"id":"IDFM:72037","arrival":"18:29:45","departure":"18:29:45","sequence":0},{"id":"IDFM:72033","arrival":"18:30:45","departure":"18:31:15","sequence":1},{"id":"IDFM:72028","arrival":"18:32:55","departure":"18:33:25","sequence":2},{"id":"IDFM:73312","arrival":"18:35:05","departure":"18:35:35","sequence":3},{"id":"IDFM:73334","arrival":"18:37:15","departure":"18:37:45","sequence":4},{"id":"IDFM:73360","arrival":"18:39:15","departure":"18:40:15","sequence":5},{"id":"IDFM:411281","arrival":"18:42:25","departure":"18:42:55","sequence":6},{"id":"IDFM:73709","arrival":"18:44:30","departure":"18:45:00","sequence":7},{"id":"IDFM:73411","arrival":"18:46:10","departure":"18:46:40","sequence":8},{"id":"IDFM:411284","arrival":"18:48:00","departure":"18:48:30","sequence":9},{"id":"IDFM:72646","arrival":"18:50:15","departure":"18:50:15","sequence":10}]}