{"id":"IDFM:TN:SNCF:1b689c73-43f5-44ce-94ce-3017ce7ed82d","headsign":"KFAR","direction":"0","monday":null,"tuesday":null,"wednesday":null,"thursday":null,"friday":null,"saturday":null,"sunday":null,"start_date":null,"end_date":null,"dates":"20220416,20220417,20220418","exceptions":null,"stops":[{"id":"IDFM:71410","arrival":"09:08:00","departure":"09:08:00","sequence":0},{"id":"IDFM:474151","arrival":"09:11:00","departure":"09:11:47","sequence":1},{"id":"IDFM:73620","arrival":"09:13:09","departure":"09:13:59","sequence":2},{"id":"IDFM:71161","arrival":"09:15:21","departure":"09:15:51","sequence":3},{"id":"IDFM:71056","arrival":"09:17:49","departure":"09:18:39","sequence":4},{"id":"IDFM:70623","arrival":"09:20:27","departure":"09:20:57","sequence":5},{"id":"IDFM:70543","arrival":"09:22:04","departure":"09:22:34","sequence":6},{"id":"IDFM:70427","arrival":"09:23:50","departure":"09:24:20","sequence":7},{"id":"IDFM:70263","arrival":"09:25:48","departure":"09:26:18","sequence":8},{"id":"IDFM:70210","arrival":"09:27:26","departure":"09:27:51","sequence":9},{"id":"IDFM:70033","arrival":"09:29:49","departure":"09:30:19","sequence":10},{"id":"IDFM:69906","arrival":"09:31:46","departure":"09:32:06","sequence":11},{"id":"IDFM:69813","arrival":"09:33:25","departure":"09:33:45","sequence":12},{"id":"IDFM:69759","arrival":"09:34:55","departure":"09:35:25","sequence":13},{"id":"IDFM:69647","arrival":"09:37:00","departure":"09:37:20","sequence":14},{"id":"IDFM:69622","arrival":"09:38:24","departure":"09:38:44","sequence":15},{"id":"IDFM:63320","arrival":"09:40:08","departure":"09:40:28","sequence":16},{"id":"IDFM:63244","arrival":"09:42:44","departure":"09:42:44","sequence":17}]}