{"id":"IDFM:TN:SNCF:e183b13f-2838-4c2a-852a-58be64a79f4d","headsign":"POMA","direction":"0","monday":0,"tuesday":0,"wednesday":0,"thursday":0,"friday":0,"saturday":1,"sunday":1,"start_date":20220402,"end_date":20220410,"dates":null,"exceptions":null,"stops":[{"id":"IDFM:61410","arrival":"15:57:30","departure":"15:57:30","sequence":0},{"id":"IDFM:61480","arrival":"16:00:50","departure":"16:01:30","sequence":1},{"id":"IDFM:61579","arrival":"16:05:10","departure":"16:06:10","sequence":2},{"id":"IDFM:61727","arrival":"16:11:40","departure":"16:12:20","sequence":3},{"id":"IDFM:61926","arrival":"16:17:00","departure":"16:18:00","sequence":4},{"id":"IDFM:73626","arrival":"16:44:30","departure":"16:44:30","sequence":5}]}