{"id":"IDFM:TN:SNCF:4656f2e4-f1ad-41c9-a63a-5590fae4c82c","headsign":"QIWI","direction":"0","monday":1,"tuesday":1,"wednesday":1,"thursday":1,"friday":1,"saturday":0,"sunday":0,"start_date":20220401,"end_date":20220429,"dates":null,"exceptions":"20220418","stops":[{"id":"IDFM:64589","arrival":"19:45:55","departure":"19:45:55","sequence":0},{"id":"IDFM:64582","arrival":"19:48:35","departure":"19:49:05","sequence":1},{"id":"IDFM:64514","arrival":"19:50:37","departure":"19:51:07","sequence":2},{"id":"IDFM:64483","arrival":"19:52:53","departure":"19:53:23","sequence":3},{"id":"IDFM:70902","arrival":"19:54:53","departure":"19:55:38","sequence":4},{"id":"IDFM:70940","arrival":"19:57:30","departure":"19:58:05","sequence":5},{"id":"IDFM:70956","arrival":"19:59:48","departure":"20:00:28","sequence":6},{"id":"IDFM:70945","arrival":"20:02:07","departure":"20:02:47","sequence":7},{"id":"IDFM:71517","arrival":"20:04:24","departure":"20:05:09","sequence":8},{"id":"IDFM:71347","arrival":"20:08:42","departure":"20:09:17","sequence":9},{"id":"IDFM:478926","arrival":"20:11:43","departure":"20:12:23","sequence":10},{"id":"IDFM:474151","arrival":"20:14:18","departure":"20:15:03","sequence":11},{"id":"IDFM:73626","arrival":"20:17:33","departure":"20:18:13","sequence":12},{"id":"IDFM:71673","arrival":"20:20:14","departure":"20:20:54","sequence":13},{"id":"IDFM:71651","arrival":"20:23:27","departure":"20:23:57","sequence":14},{"id":"IDFM:71718","arrival":"20:27:43","departure":"20:28:18","sequence":15},{"id":"IDFM:73190","arrival":"20:30:27","departure":"20:30:57","sequence":16},{"id":"IDFM:73166","arrival":"20:32:27","departure":"20:32:52","sequence":17},{"id":"IDFM:412697","arrival":"20:34:55","departure":"20:35:30","sequence":18},{"id":"IDFM:73163","arrival":"20:37:45","departure":"20:38:15","sequence":19},{"id":"IDFM:68153","arrival":"20:40:41","departure":"20:41:06","sequence":20},{"id":"IDFM:68123","arrival":"20:42:41","departure":"20:43:06","sequence":21},{"id":"IDFM:68129","arrival":"20:44:51","departure":"20:45:51","sequence":22},{"id":"IDFM:68105","arrival":"20:48:59","departure":"20:49:39","sequence":23},{"id":"IDFM:68266","arrival":"20:53:14","departure":"20:53:54","sequence":24},{"id":"IDFM:68385","arrival":"20:55:58","departure":"20:55:58","sequence":25}]}