{"id":"IDFM:TN:SNCF:7b9c6470-e317-4952-891b-dafdfdf583f4","headsign":"NOTE","direction":"0","monday":1,"tuesday":1,"wednesday":1,"thursday":1,"friday":1,"saturday":0,"sunday":0,"start_date":20220401,"end_date":20220429,"dates":null,"exceptions":"20220418","stops":[{"id":"IDFM:64883","arrival":"21:03:00","departure":"21:03:00","sequence":0},{"id":"IDFM:65190","arrival":"21:07:10","departure":"21:07:40","sequence":1},{"id":"IDFM:65048","arrival":"21:11:00","departure":"21:11:30","sequence":2},{"id":"IDFM:64918","arrival":"21:13:00","departure":"21:13:30","sequence":3},{"id":"IDFM:64741","arrival":"21:16:00","departure":"21:16:30","sequence":4},{"id":"IDFM:70945","arrival":"21:20:30","departure":"21:22:30","sequence":5},{"id":"IDFM:71517","arrival":"21:24:07","departure":"21:24:37","sequence":6},{"id":"IDFM:71347","arrival":"21:28:10","departure":"21:28:40","sequence":7},{"id":"IDFM:478926","arrival":"21:31:06","departure":"21:31:36","sequence":8},{"id":"IDFM:474151","arrival":"21:33:31","departure":"21:34:01","sequence":9},{"id":"IDFM:73626","arrival":"21:36:31","departure":"21:37:01","sequence":10},{"id":"IDFM:71673","arrival":"21:39:02","departure":"21:39:32","sequence":11},{"id":"IDFM:71651","arrival":"21:42:05","departure":"21:42:35","sequence":12},{"id":"IDFM:71630","arrival":"21:44:53","departure":"21:45:13","sequence":13},{"id":"IDFM:71590","arrival":"21:46:43","departure":"21:47:03","sequence":14},{"id":"IDFM:70640","arrival":"21:48:48","departure":"21:49:08","sequence":15},{"id":"IDFM:70393","arrival":"21:51:00","departure":"21:51:20","sequence":16},{"id":"IDFM:70359","arrival":"21:52:40","departure":"21:53:00","sequence":17},{"id":"IDFM:73042","arrival":"21:54:52","departure":"21:55:12","sequence":18},{"id":"IDFM:72998","arrival":"21:56:49","departure":"21:57:49","sequence":19},{"id":"IDFM:72929","arrival":"22:00:13","departure":"22:00:33","sequence":20},{"id":"IDFM:72881","arrival":"22:03:22","departure":"22:03:22","sequence":21}]}