{"id":"IDFM:TN:SNCF:99119b45-295b-410d-b315-c069e52acc62","headsign":"VOPA","direction":"0","monday":0,"tuesday":0,"wednesday":0,"thursday":0,"friday":0,"saturday":1,"sunday":1,"start_date":20220402,"end_date":20220418,"dates":"20220418","exceptions":"20220409,20220410","stops":[{"id":"IDFM:60309","arrival":"18:39:00","departure":"18:39:00","sequence":0},{"id":"IDFM:60422","arrival":"18:42:00","departure":"18:42:40","sequence":1},{"id":"IDFM:60450","arrival":"18:44:40","departure":"18:45:30","sequence":2},{"id":"IDFM:60542","arrival":"18:48:00","departure":"18:48:40","sequence":3},{"id":"IDFM:60797","arrival":"18:51:20","departure":"18:52:10","sequence":4},{"id":"IDFM:60981","arrival":"18:56:20","departure":"18:57:00","sequence":5},{"id":"IDFM:478505","arrival":"18:59:00","departure":"19:00:00","sequence":6},{"id":"IDFM:63071","arrival":"19:03:00","departure":"19:04:00","sequence":7},{"id":"IDFM:69568","arrival":"19:08:10","departure":"19:09:10","sequence":8},{"id":"IDFM:69671","arrival":"19:11:20","departure":"19:12:00","sequence":9},{"id":"IDFM:69950","arrival":"19:15:00","departure":"19:15:40","sequence":10},{"id":"IDFM:73624","arrival":"19:18:00","departure":"19:18:50","sequence":11},{"id":"IDFM:73625","arrival":"19:20:50","departure":"19:21:50","sequence":12},{"id":"IDFM:73626","arrival":"19:27:20","departure":"19:28:50","sequence":13},{"id":"IDFM:474151","arrival":"19:32:20","departure":"19:33:30","sequence":14},{"id":"IDFM:71410","arrival":"19:36:30","departure":"19:38:00","sequence":15},{"id":"IDFM:72206","arrival":"19:42:00","departure":"19:43:00","sequence":16},{"id":"IDFM:72323","arrival":"19:45:20","departure":"19:46:20","sequence":17},{"id":"IDFM:72787","arrival":"19:50:10","departure":"19:51:10","sequence":18},{"id":"IDFM:65582","arrival":"19:53:30","departure":"19:54:30","sequence":19},{"id":"IDFM:66009","arrival":"19:58:20","departure":"19:58:20","sequence":20}]}