{"id":"IDFM:TN:SNCF:a4099b2a-cb7e-415d-a74f-8655d98f6066","headsign":"VICK","direction":"0","monday":null,"tuesday":null,"wednesday":null,"thursday":null,"friday":null,"saturday":null,"sunday":null,"start_date":null,"end_date":null,"dates":"20220416,20220417,20220418","exceptions":null,"stops":[{"id":"IDFM:71274","arrival":"13:34:20","departure":"13:34:20","sequence":0},{"id":"IDFM:71271","arrival":"13:35:50","departure":"13:36:30","sequence":1},{"id":"IDFM:73844","arrival":"13:38:00","departure":"13:38:40","sequence":2},{"id":"IDFM:71150","arrival":"13:40:40","departure":"13:41:40","sequence":3},{"id":"IDFM:74002","arrival":"13:43:30","departure":"13:44:10","sequence":4},{"id":"IDFM:71016","arrival":"13:45:50","departure":"13:46:50","sequence":5},{"id":"IDFM:70612","arrival":"13:48:40","departure":"13:49:30","sequence":6},{"id":"IDFM:70412","arrival":"13:51:40","departure":"13:52:20","sequence":7},{"id":"IDFM:69487","arrival":"13:56:20","departure":"13:57:00","sequence":8},{"id":"IDFM:63923","arrival":"13:58:20","departure":"13:59:00","sequence":9},{"id":"IDFM:63886","arrival":"14:01:00","departure":"14:01:40","sequence":10},{"id":"IDFM:73721","arrival":"14:04:50","departure":"14:04:50","sequence":11}]}