{"id":"IDFM:TN:SNCF:df63b31a-485b-47b6-b145-59f4eba9dbae","headsign":"DOPA","direction":"0","monday":0,"tuesday":0,"wednesday":0,"thursday":0,"friday":0,"saturday":1,"sunday":1,"start_date":20220402,"end_date":20220418,"dates":"20220418","exceptions":null,"stops":[{"id":"IDFM:60309","arrival":"20:09:00","departure":"20:09:00","sequence":0},{"id":"IDFM:60422","arrival":"20:12:00","departure":"20:12:40","sequence":1},{"id":"IDFM:60450","arrival":"20:14:40","departure":"20:15:30","sequence":2},{"id":"IDFM:60542","arrival":"20:18:00","departure":"20:18:40","sequence":3},{"id":"IDFM:60797","arrival":"20:21:20","departure":"20:22:10","sequence":4},{"id":"IDFM:60981","arrival":"20:26:20","departure":"20:27:00","sequence":5},{"id":"IDFM:478505","arrival":"20:29:00","departure":"20:30:00","sequence":6},{"id":"IDFM:63071","arrival":"20:33:00","departure":"20:34:00","sequence":7},{"id":"IDFM:69568","arrival":"20:38:10","departure":"20:39:10","sequence":8},{"id":"IDFM:69671","arrival":"20:41:20","departure":"20:42:00","sequence":9},{"id":"IDFM:69950","arrival":"20:45:00","departure":"20:45:40","sequence":10},{"id":"IDFM:73624","arrival":"20:48:00","departure":"20:48:50","sequence":11},{"id":"IDFM:73625","arrival":"20:50:50","departure":"20:51:50","sequence":12},{"id":"IDFM:73626","arrival":"20:58:00","departure":"20:58:00","sequence":13}]}