{"id":"IDFM:TN:SNCF:667bff79-2938-4dc6-b26e-847361ee9c1b","headsign":"Bondy","direction":"0","monday":1,"tuesday":1,"wednesday":1,"thursday":1,"friday":1,"saturday":0,"sunday":0,"start_date":20220404,"end_date":20220429,"dates":null,"exceptions":null,"stops":[{"id":"IDFM:72646","arrival":"19:01:30","departure":"19:01:30","sequence":0},{"id":"IDFM:411284","arrival":"19:03:05","departure":"19:03:35","sequence":1},{"id":"IDFM:73411","arrival":"19:04:55","departure":"19:05:25","sequence":2},{"id":"IDFM:73709","arrival":"19:06:35","departure":"19:07:05","sequence":3},{"id":"IDFM:411281","arrival":"19:08:40","departure":"19:09:10","sequence":4},{"id":"IDFM:73360","arrival":"19:11:30","departure":"19:12:30","sequence":5},{"id":"IDFM:73334","arrival":"19:13:50","departure":"19:14:20","sequence":6},{"id":"IDFM:73312","arrival":"19:16:00","departure":"19:16:30","sequence":7},{"id":"IDFM:72028","arrival":"19:18:10","departure":"19:18:40","sequence":8},{"id":"IDFM:72033","arrival":"19:20:30","departure":"19:21:00","sequence":9},{"id":"IDFM:72037","arrival":"19:22:00","departure":"19:22:00","sequence":10}]}