{"id":"IDFM:TN:SNCF:0088ed8c-42d2-4c21-85b4-6bab128e9d78","headsign":"CUPI","direction":"0","monday":null,"tuesday":null,"wednesday":null,"thursday":null,"friday":null,"saturday":null,"sunday":null,"start_date":null,"end_date":null,"dates":"20220416,20220417,20220418","exceptions":null,"stops":[{"id":"IDFM:71359","arrival":"15:45:00","departure":"15:45:00","sequence":0},{"id":"IDFM:72041","arrival":"15:58:00","departure":"15:59:00","sequence":1},{"id":"IDFM:72037","arrival":"16:00:50","departure":"16:01:30","sequence":2},{"id":"IDFM:73297","arrival":"16:04:10","departure":"16:04:50","sequence":3},{"id":"IDFM:73278","arrival":"16:06:20","departure":"16:07:00","sequence":4},{"id":"IDFM:73266","arrival":"16:09:20","departure":"16:10:00","sequence":5},{"id":"IDFM:68407","arrival":"16:12:20","departure":"16:12:20","sequence":6}]}