{"id":"IDFM:TN:SNCF:15b56512-a664-4c39-9ad2-d478b0406915","headsign":"JULO","direction":"0","monday":0,"tuesday":0,"wednesday":0,"thursday":0,"friday":0,"saturday":0,"sunday":1,"start_date":20220424,"end_date":20220424,"dates":null,"exceptions":null,"stops":[{"id":"IDFM:72206","arrival":"22:59:50","departure":"22:59:50","sequence":0},{"id":"IDFM:71410","arrival":"23:05:00","departure":"23:06:30","sequence":1},{"id":"IDFM:474151","arrival":"23:09:30","departure":"23:10:50","sequence":2},{"id":"IDFM:73626","arrival":"23:15:00","departure":"23:19:30","sequence":3},{"id":"IDFM:73625","arrival":"23:26:10","departure":"23:26:50","sequence":4},{"id":"IDFM:73624","arrival":"23:28:50","departure":"23:29:30","sequence":5},{"id":"IDFM:69568","arrival":"23:35:30","departure":"23:36:10","sequence":6},{"id":"IDFM:63071","arrival":"23:39:40","departure":"23:40:40","sequence":7},{"id":"IDFM:478505","arrival":"23:43:40","departure":"23:43:40","sequence":8}]}