{"id":"IDFM:TN:SNCF:cf539138-0fa8-4da8-9bcb-867e86cdc613","headsign":"HOCI","direction":"0","monday":0,"tuesday":0,"wednesday":0,"thursday":0,"friday":0,"saturday":1,"sunday":1,"start_date":20220402,"end_date":20220430,"dates":null,"exceptions":"20220416,20220417","stops":[{"id":"IDFM:68407","arrival":"19:00:30","departure":"19:00:30","sequence":0},{"id":"IDFM:73266","arrival":"19:02:50","departure":"19:03:30","sequence":1},{"id":"IDFM:73278","arrival":"19:05:50","departure":"19:06:30","sequence":2},{"id":"IDFM:73297","arrival":"19:08:00","departure":"19:08:40","sequence":3},{"id":"IDFM:72037","arrival":"19:11:20","departure":"19:12:00","sequence":4},{"id":"IDFM:72041","arrival":"19:14:00","departure":"19:15:00","sequence":5},{"id":"IDFM:72421","arrival":"19:19:00","departure":"19:19:50","sequence":6},{"id":"IDFM:73798","arrival":"19:22:40","departure":"19:23:30","sequence":7},{"id":"IDFM:478733","arrival":"19:26:30","departure":"19:27:30","sequence":8},{"id":"IDFM:73688","arrival":"19:32:00","departure":"19:32:00","sequence":9}]}