{"id":"IDFM:TN:SNCF:1511d7bb-6286-49b3-a88f-064cc62e12a7","headsign":"Garges - Sarcelles RER","direction":"0","monday":0,"tuesday":0,"wednesday":0,"thursday":0,"friday":0,"saturday":1,"sunday":1,"start_date":20220409,"end_date":20220424,"dates":null,"exceptions":"20220416,20220417","stops":[{"id":"IDFM:72206","arrival":"11:25:00","departure":"11:25:00","sequence":0},{"id":"IDFM:72787","arrival":"11:43:00","departure":"11:43:00","sequence":1},{"id":"IDFM:65582","arrival":"12:00:00","departure":"12:00:00","sequence":2}]}