{"id":"IDFM:TN:SNCF:52b79dcd-ef25-4956-9fd7-f8c1f4402dcd","headsign":"701","direction":"1","monday":1,"tuesday":1,"wednesday":1,"thursday":1,"friday":1,"saturday":0,"sunday":1,"start_date":20220403,"end_date":20220429,"dates":null,"exceptions":null,"stops":[{"id":"IDFM:72641","arrival":"20:01:00","departure":"20:01:00","sequence":0},{"id":"IDFM:426093","arrival":"20:03:40","departure":"20:04:00","sequence":1},{"id":"IDFM:426083","arrival":"20:06:10","departure":"20:06:30","sequence":2},{"id":"IDFM:72787","arrival":"20:08:40","departure":"20:09:00","sequence":3},{"id":"IDFM:72396","arrival":"20:11:10","departure":"20:11:30","sequence":4},{"id":"IDFM:65227","arrival":"20:13:00","departure":"20:13:20","sequence":5},{"id":"IDFM:72383","arrival":"20:15:10","departure":"20:15:10","sequence":6}]}