{"id":"IDFM:TN:SNCF:43cb4a2b-9612-4cd4-9bd1-874269d015b1","headsign":"Hôpital de Montfermeil","direction":"0","monday":0,"tuesday":0,"wednesday":0,"thursday":0,"friday":0,"saturday":1,"sunday":1,"start_date":20220402,"end_date":20220430,"dates":null,"exceptions":null,"stops":[{"id":"IDFM:72037","arrival":"17:37:30","departure":"17:37:30","sequence":0},{"id":"IDFM:72033","arrival":"17:38:30","departure":"17:39:00","sequence":1},{"id":"IDFM:72028","arrival":"17:40:40","departure":"17:41:10","sequence":2},{"id":"IDFM:73312","arrival":"17:42:50","departure":"17:43:20","sequence":3},{"id":"IDFM:73334","arrival":"17:45:00","departure":"17:45:30","sequence":4},{"id":"IDFM:73360","arrival":"17:47:00","departure":"17:48:00","sequence":5},{"id":"IDFM:73354","arrival":"17:50:35","departure":"17:51:05","sequence":6},{"id":"IDFM:73362","arrival":"17:53:25","departure":"17:53:55","sequence":7},{"id":"IDFM:73364","arrival":"17:55:10","departure":"17:55:40","sequence":8},{"id":"IDFM:477288","arrival":"17:57:55","departure":"17:58:25","sequence":9},{"id":"IDFM:73350","arrival":"18:00:00","departure":"18:00:30","sequence":10},{"id":"IDFM:477278","arrival":"18:01:45","departure":"18:02:15","sequence":11},{"id":"IDFM:477285","arrival":"18:03:45","departure":"18:05:50","sequence":12},{"id":"IDFM:478648","arrival":"18:07:15","departure":"18:07:45","sequence":13},{"id":"IDFM:73329","arrival":"18:10:45","departure":"18:10:45","sequence":14}]}