{"id":"IDFM:TN:SNCF:730067a5-8ec4-4f10-b2da-28b200d3cad5","headsign":"AEKY","direction":"1","monday":1,"tuesday":1,"wednesday":1,"thursday":1,"friday":1,"saturday":0,"sunday":0,"start_date":20220401,"end_date":20220429,"dates":null,"exceptions":"20220418","stops":[{"id":"IDFM:411397","arrival":"06:54:20","departure":"06:54:20","sequence":0},{"id":"IDFM:411388","arrival":"06:59:00","departure":"06:59:40","sequence":1},{"id":"IDFM:411391","arrival":"07:04:30","departure":"07:05:10","sequence":2},{"id":"IDFM:411406","arrival":"07:09:30","departure":"07:10:10","sequence":3},{"id":"IDFM:69254","arrival":"07:15:10","departure":"07:15:50","sequence":4},{"id":"IDFM:69196","arrival":"07:18:30","departure":"07:19:10","sequence":5},{"id":"IDFM:69136","arrival":"07:21:10","departure":"07:21:50","sequence":6},{"id":"IDFM:69065","arrival":"07:24:10","departure":"07:25:10","sequence":7},{"id":"IDFM:72646","arrival":"07:34:00","departure":"07:35:00","sequence":8},{"id":"IDFM:71410","arrival":"07:49:30","departure":"07:49:30","sequence":9}]}