{"id":"IDFM:TN:SNCF:af777433-56e6-44ea-852e-4c3636a60781","headsign":"EPAF","direction":"0","monday":0,"tuesday":0,"wednesday":0,"thursday":0,"friday":0,"saturday":1,"sunday":1,"start_date":20220402,"end_date":20220430,"dates":null,"exceptions":"20220416,20220417","stops":[{"id":"IDFM:62978","arrival":"18:54:09","departure":"18:54:09","sequence":0},{"id":"IDFM:62951","arrival":"18:56:34","departure":"18:57:09","sequence":1},{"id":"IDFM:62890","arrival":"18:59:46","departure":"19:00:16","sequence":2},{"id":"IDFM:62825","arrival":"19:01:40","departure":"19:02:10","sequence":3},{"id":"IDFM:62851","arrival":"19:03:32","departure":"19:04:02","sequence":4},{"id":"IDFM:62892","arrival":"19:05:41","departure":"19:06:21","sequence":5},{"id":"IDFM:63025","arrival":"19:08:04","departure":"19:08:24","sequence":6},{"id":"IDFM:63029","arrival":"19:10:01","departure":"19:10:21","sequence":7},{"id":"IDFM:63067","arrival":"19:12:25","departure":"19:12:50","sequence":8},{"id":"IDFM:63175","arrival":"19:14:11","departure":"19:14:36","sequence":9},{"id":"IDFM:63244","arrival":"19:16:18","departure":"19:17:08","sequence":10},{"id":"IDFM:69759","arrival":"19:21:23","departure":"19:21:53","sequence":11},{"id":"IDFM:69813","arrival":"19:23:04","departure":"19:23:29","sequence":12},{"id":"IDFM:70033","arrival":"19:25:40","departure":"19:26:10","sequence":13},{"id":"IDFM:70623","arrival":"19:31:16","departure":"19:31:46","sequence":14},{"id":"IDFM:71056","arrival":"19:33:36","departure":"19:34:26","sequence":15},{"id":"IDFM:71161","arrival":"19:36:23","departure":"19:36:53","sequence":16},{"id":"IDFM:73620","arrival":"19:38:29","departure":"19:39:09","sequence":17},{"id":"IDFM:474151","arrival":"19:40:29","departure":"19:41:00","sequence":18},{"id":"IDFM:71410","arrival":"19:44:00","departure":"19:45:00","sequence":19},{"id":"IDFM:72211","arrival":"19:49:20","departure":"19:50:10","sequence":20},{"id":"IDFM:72598","arrival":"19:52:00","departure":"19:52:30","sequence":21},{"id":"IDFM:72641","arrival":"19:55:20","departure":"19:55:50","sequence":22},{"id":"IDFM:72652","arrival":"19:58:00","departure":"19:58:30","sequence":23},{"id":"IDFM:72648","arrival":"20:00:10","departure":"20:00:40","sequence":24},{"id":"IDFM:72646","arrival":"20:02:20","departure":"20:03:10","sequence":25},{"id":"IDFM:73491","arrival":"20:05:50","departure":"20:06:20","sequence":26},{"id":"IDFM:73547","arrival":"20:08:10","departure":"20:08:40","sequence":27},{"id":"IDFM:73568","arrival":"20:10:10","departure":"20:11:00","sequence":28},{"id":"IDFM:73596","arrival":"20:15:50","departure":"20:16:50","sequence":29},{"id":"IDFM:73699","arrival":"20:19:20","departure":"20:19:20","sequence":30}]}