{"id":"IDFM:TN:SNCF:39f4dc88-8e0d-4615-9317-e87bb634b372","headsign":"ORKA","direction":"0","monday":1,"tuesday":1,"wednesday":1,"thursday":1,"friday":1,"saturday":0,"sunday":0,"start_date":20220401,"end_date":20220429,"dates":null,"exceptions":"20220418","stops":[{"id":"IDFM:71517","arrival":"19:14:29","departure":"19:14:29","sequence":0},{"id":"IDFM:71347","arrival":"19:17:49","departure":"19:18:29","sequence":1},{"id":"IDFM:478926","arrival":"19:21:09","departure":"19:21:54","sequence":2},{"id":"IDFM:474151","arrival":"19:24:01","departure":"19:24:56","sequence":3},{"id":"IDFM:73626","arrival":"19:27:36","departure":"19:28:21","sequence":4},{"id":"IDFM:71673","arrival":"19:30:27","departure":"19:31:12","sequence":5},{"id":"IDFM:71651","arrival":"19:33:53","departure":"19:34:28","sequence":6},{"id":"IDFM:71718","arrival":"19:38:16","departure":"19:39:11","sequence":7},{"id":"IDFM:73190","arrival":"19:41:20","departure":"19:41:55","sequence":8},{"id":"IDFM:73166","arrival":"19:43:25","departure":"19:43:55","sequence":9},{"id":"IDFM:412697","arrival":"19:45:58","departure":"19:46:38","sequence":10},{"id":"IDFM:73163","arrival":"19:48:53","departure":"19:49:33","sequence":11},{"id":"IDFM:68153","arrival":"19:51:59","departure":"19:52:29","sequence":12},{"id":"IDFM:68123","arrival":"19:54:04","departure":"19:54:34","sequence":13},{"id":"IDFM:68129","arrival":"19:56:19","departure":"19:56:19","sequence":14}]}