{"id":"IDFM:TN:SNCF:bade2738-1648-4f00-beb1-5c37e89f2af9","headsign":"LOLI","direction":"0","monday":0,"tuesday":0,"wednesday":0,"thursday":0,"friday":0,"saturday":1,"sunday":1,"start_date":20220402,"end_date":20220430,"dates":"20220418","exceptions":null,"stops":[{"id":"IDFM:66335","arrival":"22:55:40","departure":"22:55:40","sequence":0},{"id":"IDFM:66005","arrival":"22:59:00","departure":"22:59:40","sequence":1},{"id":"IDFM:65752","arrival":"23:01:40","departure":"23:02:20","sequence":2},{"id":"IDFM:65669","arrival":"23:04:10","departure":"23:05:10","sequence":3},{"id":"IDFM:65305","arrival":"23:08:10","departure":"23:08:50","sequence":4},{"id":"IDFM:72383","arrival":"23:10:50","departure":"23:11:30","sequence":5},{"id":"IDFM:72303","arrival":"23:14:00","departure":"23:14:40","sequence":6},{"id":"IDFM:72225","arrival":"23:16:20","departure":"23:17:00","sequence":7},{"id":"IDFM:72126","arrival":"23:20:10","departure":"23:21:10","sequence":8},{"id":"IDFM:71545","arrival":"23:23:30","departure":"23:24:20","sequence":9},{"id":"IDFM:71453","arrival":"23:26:50","departure":"23:27:40","sequence":10},{"id":"IDFM:71379","arrival":"23:29:40","departure":"23:30:40","sequence":11},{"id":"IDFM:71321","arrival":"23:33:00","departure":"23:33:40","sequence":12},{"id":"IDFM:71286","arrival":"23:34:50","departure":"23:35:30","sequence":13},{"id":"IDFM:71229","arrival":"23:37:10","departure":"23:37:50","sequence":14},{"id":"IDFM:71212","arrival":"23:38:50","departure":"23:39:50","sequence":15},{"id":"IDFM:73844","arrival":"23:41:40","departure":"23:42:20","sequence":16},{"id":"IDFM:71271","arrival":"23:44:00","departure":"23:44:40","sequence":17},{"id":"IDFM:71274","arrival":"23:46:50","departure":"23:46:50","sequence":18}]}