{"id":"IDFM:TN:SNCF:9f15eaa7-12d3-4759-aa9f-575ea78180e5","headsign":"Survilliers - Fosses","direction":"0","monday":0,"tuesday":0,"wednesday":0,"thursday":0,"friday":0,"saturday":1,"sunday":1,"start_date":20220409,"end_date":20220424,"dates":null,"exceptions":"20220416,20220417","stops":[{"id":"IDFM:72206","arrival":"19:43:00","departure":"19:43:00","sequence":0},{"id":"IDFM:65582","arrival":"20:13:00","departure":"20:13:00","sequence":1},{"id":"IDFM:66009","arrival":"20:30:00","departure":"20:30:00","sequence":2},{"id":"IDFM:66535","arrival":"20:46:00","departure":"20:46:00","sequence":3},{"id":"IDFM:69300","arrival":"21:02:00","departure":"21:02:00","sequence":4},{"id":"IDFM:69450","arrival":"21:15:00","departure":"21:15:00","sequence":5}]}