{"id":"IDFM:TN:SNCF:8e90f81b-c52b-4f4e-bba8-eedb2c756388","headsign":"INCA","direction":"0","monday":1,"tuesday":1,"wednesday":1,"thursday":1,"friday":1,"saturday":0,"sunday":0,"start_date":20220401,"end_date":20220429,"dates":null,"exceptions":"20220418","stops":[{"id":"IDFM:63244","arrival":"16:19:59","departure":"16:19:59","sequence":0},{"id":"IDFM:63320","arrival":"16:21:44","departure":"16:22:14","sequence":1},{"id":"IDFM:69622","arrival":"16:23:42","departure":"16:24:12","sequence":2},{"id":"IDFM:69647","arrival":"16:25:17","departure":"16:25:42","sequence":3},{"id":"IDFM:69759","arrival":"16:27:18","departure":"16:28:03","sequence":4},{"id":"IDFM:69813","arrival":"16:29:14","departure":"16:29:49","sequence":5},{"id":"IDFM:69906","arrival":"16:31:07","departure":"16:31:32","sequence":6},{"id":"IDFM:70033","arrival":"16:33:01","departure":"16:33:41","sequence":7},{"id":"IDFM:70210","arrival":"16:35:40","departure":"16:36:10","sequence":8},{"id":"IDFM:70263","arrival":"16:37:20","departure":"16:37:55","sequence":9},{"id":"IDFM:70427","arrival":"16:39:28","departure":"16:39:58","sequence":10},{"id":"IDFM:70543","arrival":"16:41:15","departure":"16:41:45","sequence":11},{"id":"IDFM:70623","arrival":"16:42:51","departure":"16:43:26","sequence":12},{"id":"IDFM:71056","arrival":"16:45:16","departure":"16:46:06","sequence":13},{"id":"IDFM:71161","arrival":"16:48:03","departure":"16:48:33","sequence":14},{"id":"IDFM:73620","arrival":"16:50:09","departure":"16:50:59","sequence":15},{"id":"IDFM:474151","arrival":"16:52:19","departure":"16:53:00","sequence":16},{"id":"IDFM:71410","arrival":"16:56:00","departure":"16:57:10","sequence":17},{"id":"IDFM:72211","arrival":"17:01:10","departure":"17:02:00","sequence":18},{"id":"IDFM:72598","arrival":"17:04:00","departure":"17:04:30","sequence":19},{"id":"IDFM:72641","arrival":"17:07:20","departure":"17:07:50","sequence":20},{"id":"IDFM:72652","arrival":"17:10:00","departure":"17:10:30","sequence":21},{"id":"IDFM:72648","arrival":"17:12:10","departure":"17:12:40","sequence":22},{"id":"IDFM:72646","arrival":"17:14:20","departure":"17:15:20","sequence":23},{"id":"IDFM:73439","arrival":"17:18:10","departure":"17:18:40","sequence":24},{"id":"IDFM:73482","arrival":"17:21:10","departure":"17:21:40","sequence":25},{"id":"IDFM:68916","arrival":"17:24:20","departure":"17:24:50","sequence":26},{"id":"IDFM:69065","arrival":"17:28:30","departure":"17:28:30","sequence":27}]}