{"id":"OCESN7411F537861:2022-03-04T20:33:16Z","headsign":"7411","direction":"1","monday":null,"tuesday":null,"wednesday":null,"thursday":null,"friday":null,"saturday":null,"sunday":null,"start_date":null,"end_date":null,"dates":"20220307,20220402,20220409,20220409,20220416,20220416,20220423,20220430,20220430,20220507,20220507,20220604,20220611,20220618,20220618,20220625","exceptions":null,"stops":[{"id":"StopArea:OCE87271007","arrival":"08:16:00","departure":"08:16:00","sequence":0},{"id":"StopArea:OCE87286005","arrival":"09:19:00","departure":"09:19:00","sequence":1}]}