{"id":"OCESN7085F713759:2022-03-02T20:32:55Z","headsign":"7085","direction":"1","monday":null,"tuesday":null,"wednesday":null,"thursday":null,"friday":null,"saturday":null,"sunday":null,"start_date":null,"end_date":null,"dates":"20220312,20220326,20220402,20220409,20220416,20220423,20220430,20220507,20220514,20220521,20220526,20220528,20220604","exceptions":null,"stops":[{"id":"StopArea:OCE87271007","arrival":"20:46:00","departure":"20:46:00","sequence":0},{"id":"StopArea:OCE87286005","arrival":"21:48:00","departure":"21:48:00","sequence":1}]}