{"id":"OCESN3332F634789:2022-03-16T20:33:02Z","headsign":"3332","direction":"0","monday":null,"tuesday":null,"wednesday":null,"thursday":null,"friday":null,"saturday":null,"sunday":null,"start_date":null,"end_date":null,"dates":"20220416,20220418,20220423,20220423,20220424,20220429,20220430,20220430,20220507,20220507,20220508,20220618","exceptions":null,"stops":[{"id":"StopArea:OCE87444000","arrival":"08:58:00","departure":"08:58:00","sequence":0},{"id":"StopArea:OCE87384008","arrival":"11:02:00","departure":"11:02:00","sequence":1}]}