{"id":"OCESN23806F795847:2022-03-23T20:45:58Z","headsign":"23806","direction":"0","monday":null,"tuesday":null,"wednesday":null,"thursday":null,"friday":null,"saturday":null,"sunday":null,"start_date":null,"end_date":null,"dates":"20220418,20220423,20220430,20220501,20220507,20220508,20220514,20220515,20220521,20220522,20220528,20220529,20220604,20220611,20220618,20220625","exceptions":null,"stops":[{"id":"StopArea:OCE87193003","arrival":"14:35:00","departure":"14:35:00","sequence":0},{"id":"StopArea:OCE87193250","arrival":"14:41:00","departure":"14:42:00","sequence":1},{"id":"StopArea:OCE87193318","arrival":"14:48:00","departure":"14:49:00","sequence":2},{"id":"StopArea:OCE87193342","arrival":"14:53:00","departure":"14:54:00","sequence":3},{"id":"StopArea:OCE87193359","arrival":"14:58:00","departure":"14:59:00","sequence":4},{"id":"StopArea:OCE87192237","arrival":"15:12:00","departure":"15:13:00","sequence":5},{"id":"StopArea:OCE87192039","arrival":"15:25:00","departure":"15:25:00","sequence":6}]}